{"urls": ["abcnews.com.co", "cognitive-improvmentnews.com/t3/", "infowars.com", "www.naturalnews.com/index.html", "prntly.com", "libertywritersnews.com", "www.huffingtonpost.com", "www.yahoo.com/news/?ref=gs", "news.google.com", "www.cnn.com", "www.nytimes.com", "www.foxnews.com", "www.nbcnews.com", "http://abcnews.com.co/", "http://abcnews.com.co/breaking-capitol-hill-shooter-identified-as-right-wing-extremist/"], "abcnews.com.co": {"url": "abcnews.com.co", "mtext": ["FIND"], "otext": ["FIND"], "whois": {"email": "netskrillsupport@gmail.com", "address": ["402 North 10th Street", "Phoenix", "85006", "United States"], "phone": "+48.07750365"}, "type": "Fake"}, "cognitive-improvmentnews.com/t3/": {"url": "cognitive-improvmentnews.com/t3/", "mtext": ["FIND"], "otext": ["FIND"], "whois": {"email": "cognitive-improvmentnews.com@domainsbyproxy.com", "address": ["14455 N. Hayden Road", "Scottsdale", "85260", "United States"], "phone": "+1.4806242599"}, "type": "Fake"}, "infowars.com": {"url": "infowars.com", "mtext": ["FIND"], "otext": ["FIND"], "whois": {"email": "ishare_domains-brandnames@infowars.com", "address": ["PO Box 19549", "Austin", "78760", "United States"], "phone": "+1.5124394400"}, "type": "Fake"}, "www.naturalnews.com/index.html": {"url": "www.naturalnews.com/index.html", "mtext": ["FIND"], "otext": ["FIND"], "whois": {"email": "naturalnews.com@domainsbyproxy.com", "address": ["14455 N. Hayden Road", "Scottsdale", "85260", "United States"], "phone": "+1.4806242599"}, "type": "Fake"}, "prntly.com": {"url": "prntly.com", "mtext": ["FIND"], "otext": ["FIND"], "whois": {"email": "contact@privacyprotect.org", "address": ["C/O ID#10760, PO Box 16 Note", "Nobby Beach", "QLD 4218", "Australia"], "phone": "_45.36946676"}, "type": "Fake"}, "libertywritersnews.com": {"url": "libertywritersnews.com", "mtext": ["FIND"], "otext": ["FIND"], "whois": {"email": "sqgwtqvvtc@whoisprivacyprotect.com", "address": ["PO Box 639", "Kirkland", "98083", "United States"], "phone": "+1.4259740657"}, "type": "Fake"}, "www.yahoo.com/news/?ref=gs": {"url": "www.yahoo.com/news/?ref=gs", "mtext": ["FIND"], "otext": ["FIND"], "whois": {"email": "domainadmin@yahoo-inc.com", "address": ["701 First Avenue", "Sunnyvale", "94089", "United States"], "phone": "+1.4083493300"}, "type": "Real"}, "news.google.com": {"url": "news.google.com", "mtext": ["FIND"], "otext": ["FIND"], "whois": {"email": "dns-admin@google.com", "address": ["1600 Amphitheatre Parkway", "Mountain View", "94043", "United States"], "phone": "+1.6502530000"}, "type": "Real"}, "www.huffingtonpost.com": {"url": "www.huffingtonpost.com", "mtext": ["FIND"], "otext": ["FIND"], "whois": {"email": "domain-adm@corp.aol.com", "address": ["560 Broadway, 405", "New York", "10012", "United States"], "phone": "+1.7032654670"}, "type": "Real"}, "www.cnn.com": {"url": "www.cnn.com", "mtext": ["FIND"], "otext": ["FIND"], "whois": {"email": "tmgroup@turner.com", "address": ["One CNN Center", "Atlanta", "30303", "United States"], "phone": "+1.40482750000"}, "type": "Real"}, "www.nytimes.com": {"url": "www.nytimes.com", "mtext": ["FIND"], "otext": ["FIND"], "whois": {"email": "hostmaster@nytimes.com", "address": ["620 8th Avenue", "New York", "10018", "United States"], "phone": "+1.2125561234"}, "type": "Real"}, "www.foxnews.com": {"url": "www.foxnews.com", "mtext": ["FIND"], "otext": ["FIND"], "whois": {"email": "wmf@fox.com", "address": ["10201 W. Pico Boulevard", "Los Angeles", "90213", "United States"], "phone": "+1.31036910000"}, "type": "Real"}, "www.nbcnews.com": {"url": "www.nbcnews.com", "mtext": ["FIND"], "otext": ["FIND"], "whois": {"email": "domain.admin@nbcuni.com", "address": ["904 Sylvan Avenue", "Englewood Cliffs", "07632", "United States"], "phone": "+1.81877710000"}, "type": "Real"}, "http://abcnews.com.co/": {"url": "http://abcnews.com.co/", "mtext": [], "otext": ["News - ABC News"], "whois": {"email": "FIND", "address": ["FIND", "FIND", "FIND", "FIND"], "phone": "FIND"}, "type": "Fake"}, "http://abcnews.com.co/breaking-capitol-hill-shooter-identified-as-right-wing-extremist/": {"url": "http://abcnews.com.co/breaking-capitol-hill-shooter-identified-as-right-wing-extremist/", "mtext": ["BREAKING: Capitol Hill Shooter Identified as Right Wing Extremist"], "otext": ["BREAKING: Capitol Hill Shooter Identified as Right Wing Extremist - ABC News", "Capitol Hill, where a white supremacist carried out an attack, injuring a police officer", "WASHINGTON DC \u00e20\u0093 Monday afternoon, an extremist carried out an attack on Capitol Hill, shooting and injuring a police officer. The man has been identified as Thomas Finnigan, a white supremacist from Maryland. He has been taken into police custody, although currently Capitol Hill, including Congress and and the White House, remain on lockdown.", "When the attack was carried out, Finnigan was described by eyewitnesses as trying to leave the visitor\u00e20\u0099enter, and advance further into either the library, Supreme Court, or even the White House.\u00e20\u009c I heard was \u00e20\u0098pletive removed] Obama! [expletive removed] liberals and ISIS! Make America great again!\u00e20\u009dhn Burke, a college student visiting the visitors center stated to ABC News. \u00e20\u009cn we heard gun shots and were immediately instructed to leave the building.\u00e20\u009d", "Thomas Finnigan is a 32 year old white supremacist linked towards having a strong affinity for Republican frontrunner Donald Trump on his Facebook. He grew up in a lower class family in Tennessee, and later moved to Maryland. Not much else is known about the shooter.\u00e20\u009cxe2\u00809s concerning, how some of our own born-and-bred American citizens are turning into terrorists over political unrest,\u00e20\u009dC political analyst Ana Cuddy said. \u00e20\u009cle in my own opinion, I must say I take no issue with the conservatives of the United States in general, this is not the first time a Donald Trump supporter specifically has carried out violent acts towards other members of the population. It is concerning to see how the Republican party has radicalized, and I hope the United States of America can learn its lesson from the treacherous acts Trump incites in our citizens.\u00e20\u009d", "UPDATE 4:00 PM EST: The lockdown has been lifted according to Capitol Police.UPDATE 4:37 PM EST: According to Capitol Police, no officer was shot. However, two tourists were injured by shrapnel.ABC news will continue to bring you updated news involving the Capitol Hill shooting as information comes to light."], "whois": {"email": "FIND", "address": ["FIND", "FIND", "FIND", "FIND"], "phone": "FIND"}, "type": "FIND"}}